rtl2/packetizer_fsm.v
module packetizer_fsm #(
    parameter BAUD_DIVISOR = 5
)(
    input clk,
    input rst,
    input fifo_empty,
    input tx_ready,
    input [7:0] fifo_data,
    output reg serial_out,
    output reg tx_busy,
    output reg rd_en
);

    // FSM states
    localparam IDLE     = 3'b000;
    localparam WAIT_RDY = 3'b001;
    localparam START    = 3'b010;
    localparam DATA     = 3'b011;
    localparam STOP     = 3'b100;
    
    reg [2:0] state = IDLE;
    reg [15:0] baud_counter = 0;
    reg [3:0] bit_counter = 0;
    reg [7:0] data_reg = 0;
    reg baud_tick;

    // Baud rate generator - FIXED TIMING
    always @(posedge clk) begin
        if (rst) begin
            baud_counter <= 0;
            baud_tick <= 0;
        end else begin
            baud_tick <= 0;  // Default
            if (state != IDLE) begin
                if (baud_counter == BAUD_DIVISOR - 1) begin
                    baud_counter <= 0;
                    baud_tick <= 1;
                end else begin
                    baud_counter <= baud_counter + 1;
                end
            end else begin
                baud_counter <= 0;
            end
        end
    end

    // FSM logic - COMPLETELY REVISED
    always @(posedge clk) begin
        if (rst) begin
            state <= IDLE;
            serial_out <= 1'b1;
            tx_busy <= 1'b0;
            rd_en <= 1'b0;
            bit_counter <= 0;
            data_reg <= 0;
        end else begin
            rd_en <= 1'b0;  // Default
            
            case (state)
                IDLE: begin
                    serial_out <= 1'b1;
                    tx_busy <= 1'b0;
                    bit_counter <= 0;
                    
                    if (!fifo_empty && tx_ready) begin
                        state <= WAIT_RDY;
                        tx_busy <= 1'b1;
                    end
                end
                
                WAIT_RDY: begin
                    // Immediately capture data when tx_ready is detected
                    data_reg <= fifo_data;
                    if (tx_ready) begin
                        rd_en <= 1'b1;  // Assert read enable
                        state <= START;
                    end
                end
                
                START: begin
                    serial_out <= 1'b0;  // Start bit
                    if (baud_tick) begin
                        state <= DATA;
                        bit_counter <= 0;
                    end
                end
                
                DATA: begin
                    // Output current bit
                    serial_out <= data_reg[bit_counter];
                    
                    if (baud_tick) begin
                        if (bit_counter == 7) begin
                            state <= STOP;
                        end else begin
                            bit_counter <= bit_counter + 1;
                        end
                    end
                end
                
                STOP: begin
                    serial_out <= 1'b1;  // Stop bit
                    if (baud_tick) begin
                        state <= IDLE;
                    end
                end
            endcase
        end
    end
endmodule

rtl2/fifo.v
module fifo #(
    parameter DATA_WIDTH = 8,
    parameter ADDR_WIDTH = 4,
    parameter DEPTH = 16
)(
    input clk,
    input rst,
    input wr_en,
    input rd_en,
    input [DATA_WIDTH-1:0] data_in,
    output reg [DATA_WIDTH-1:0] data_out,
    output full,
    output empty
);

    reg [DATA_WIDTH-1:0] mem [0:DEPTH-1];
    reg [ADDR_WIDTH:0] wr_ptr = 0;
    reg [ADDR_WIDTH:0] rd_ptr = 0;
    reg [ADDR_WIDTH:0] count = 0;

    assign full = (count == DEPTH);
    assign empty = (count == 0);

    always @(posedge clk) begin
        if (rst) begin
            wr_ptr <= 0;
            rd_ptr <= 0;
            count <= 0;
            data_out <= 0;
        end else begin
            // Write operation
            if (wr_en && !full) begin
                mem[wr_ptr[ADDR_WIDTH-1:0]] <= data_in;
                wr_ptr <= wr_ptr + 1;
                count <= count + 1;
            end
            
            // Read operation
            if (rd_en && !empty) begin
                data_out <= mem[rd_ptr[ADDR_WIDTH-1:0]];
                rd_ptr <= rd_ptr + 1;
                count <= count - 1;
            end
        end
    end
endmodule

rtl2/uart_transmitter.v
module uart_transmitter #(
    parameter BAUD_DIVISOR = 5  // 5 cycles/bit for simulation
)(
    input clk,
    input rst,
    input [7:0] data_in,
    input data_valid,
    input tx_ready,
    output serial_out,
    output fifo_full,
    output tx_busy
);

    wire fifo_empty;
    wire [7:0] fifo_data;
    wire rd_en;

    fifo u_fifo (
        .clk(clk),
        .rst(rst),
        .wr_en(data_valid),
        .rd_en(rd_en),
        .data_in(data_in),
        .data_out(fifo_data),
        .full(fifo_full),
        .empty(fifo_empty)
    );

    packetizer_fsm #(BAUD_DIVISOR) u_fsm (
        .clk(clk),
        .rst(rst),
        .fifo_empty(fifo_empty),
        .tx_ready(tx_ready),
        .fifo_data(fifo_data),
        .serial_out(serial_out),
        .tx_busy(tx_busy),
        .rd_en(rd_en)
    );

endmodule

rtl2/uart_transmitter_tb.v

module uart_transmitter_tb;
    reg clk = 0;
    reg rst;
    reg [7:0] data_in;
    reg data_valid;
    reg tx_ready;
    wire serial_out;
    wire fifo_full;
    wire tx_busy;
    
    uart_transmitter #(.BAUD_DIVISOR(5)) uut (
        .clk(clk), .rst(rst),
        .data_in(data_in), .data_valid(data_valid),
        .tx_ready(tx_ready), .serial_out(serial_out),
        .fifo_full(fifo_full), .tx_busy(tx_busy)
    );
    
    // Clock generation (50MHz = 20ns period)
    always #10 clk = ~clk;
    
    // VCD file dump
    initial begin
        $dumpfile("uart_transmitter.vcd");
        $dumpvars(0, uart_transmitter_tb);
        $dumpvars(1, uut.u_fsm);
    end
    
    // Test sequence
    initial begin
        // Initialize
        rst = 1;
        data_in = 0;
        data_valid = 0;
        tx_ready = 1;
        
        // Reset sequence
        #20 rst = 0;
        #20;
        
        // Test 1: Write data to FIFO
        $display("Writing data 0x55 to FIFO");
        data_in = 8'h55;
        data_valid = 1;
        #20 data_valid = 0;
        
        // Verify state transitions and data capture
        @(posedge uut.u_fsm.state[0]); // WAIT_RDY state
        #1; // Small delta delay for signal update
        if (uut.u_fsm.data_reg !== 8'h55)
            $error("Data not captured! Got %h, expected 55", uut.u_fsm.data_reg);
        
        @(posedge uut.u_fsm.state[1]); // START state
        #1;
        if (serial_out !== 1'b0)
            $error("Start bit not low");
            
        // Verify data bits at baud ticks
        @(posedge uut.u_fsm.baud_tick);
        #1;
        if (serial_out !== 1'b1) $error("Bit0 should be 1");
        
        @(posedge uut.u_fsm.baud_tick);
        #1;
        if (serial_out !== 1'b0) $error("Bit1 should be 0");
        
        @(posedge uut.u_fsm.baud_tick);
        #1;
        if (serial_out !== 1'b1) $error("Bit2 should be 1");
        
        @(posedge uut.u_fsm.baud_tick);
        #1;
        if (serial_out !== 1'b0) $error("Bit3 should be 0");
        
        @(posedge uut.u_fsm.baud_tick);
        #1;
        if (serial_out !== 1'b1) $error("Bit4 should be 1");
        
        @(posedge uut.u_fsm.baud_tick);
        #1;
        if (serial_out !== 1'b0) $error("Bit5 should be 0");
        
        @(posedge uut.u_fsm.baud_tick);
        #1;
        if (serial_out !== 1'b1) $error("Bit6 should be 1");
        
        @(posedge uut.u_fsm.baud_tick);
        #1;
        if (serial_out !== 1'b0) $error("Bit7 should be 0");
        
        // Verify stop bit
        @(posedge uut.u_fsm.baud_tick);
        #1;
        if (serial_out !== 1'b1)
            $error("Stop bit not high");
            
        $display("All tests passed!");
        $finish;
    end
    
    // State monitor
    always @(posedge clk) begin
        $display("Time=%0t: state=%b tx_busy=%b serial_out=%b data_reg=%h baud_tick=%b", 
                $time, uut.u_fsm.state, tx_busy, serial_out, 
                uut.u_fsm.data_reg, uut.u_fsm.baud_tick);
    end
endmodule

rtl2/uart_transmitter.vcd
$date
	Sun Jun  1 18:15:39 2025
$end
$version
	Icarus Verilog
$end
$timescale
	1s
$end
$scope module uart_transmitter_tb $end
$var wire 1 ! tx_busy $end
$var wire 1 " serial_out $end
$var wire 1 # fifo_full $end
$var reg 1 $ clk $end
$var reg 8 % data_in [7:0] $end
$var reg 1 & data_valid $end
$var reg 1 ' rst $end
$var reg 1 ( tx_ready $end
$scope module uut $end
$var wire 1 $ clk $end
$var wire 8 ) data_in [7:0] $end
$var wire 1 & data_valid $end
$var wire 1 ' rst $end
$var wire 1 ( tx_ready $end
$var wire 1 ! tx_busy $end
$var wire 1 " serial_out $end
$var wire 1 * rd_en $end
$var wire 1 # fifo_full $end
$var wire 1 + fifo_empty $end
$var wire 8 , fifo_data [7:0] $end
$scope module u_fifo $end
$var wire 1 $ clk $end
$var wire 8 - data_in [7:0] $end
$var wire 1 ' rst $end
$var wire 1 & wr_en $end
$var wire 1 * rd_en $end
$var wire 1 # full $end
$var wire 1 + empty $end
$var reg 5 . count [4:0] $end
$var reg 8 / data_out [7:0] $end
$var reg 5 0 rd_ptr [4:0] $end
$var reg 5 1 wr_ptr [4:0] $end
$upscope $end
$scope module u_fsm $end
$var wire 1 $ clk $end
$var wire 8 2 fifo_data [7:0] $end
$var wire 1 + fifo_empty $end
$var wire 1 ' rst $end
$var wire 1 ( tx_ready $end
$var reg 16 3 baud_counter [15:0] $end
$var reg 1 4 baud_tick $end
$var reg 4 5 bit_counter [3:0] $end
$var reg 8 6 data_reg [7:0] $end
$var reg 1 * rd_en $end
$var reg 1 " serial_out $end
$var reg 3 7 state [2:0] $end
$var reg 1 ! tx_busy $end
$upscope $end
$upscope $end
$upscope $end
$scope module uart_transmitter_tb $end
$scope module uut $end
$scope module u_fsm $end
$upscope $end
$upscope $end
$upscope $end
$enddefinitions $end
#0
$dumpvars
b0 7
b0 6
b0 5
x4
b0 3
bx 2
b0 1
b0 0
bx /
b0 .
b0 -
bx ,
1+
x*
b0 )
1(
1'
0&
b0 %
0$
0#
x"
x!
$end
#10
b0 ,
b0 /
b0 2
04
0*
0!
1"
1$
#20
0$
0'
#30
1$
#40
0$
1&
b1010101 %
b1010101 )
b1010101 -
#50
0+
b1 .
b1 1
1$
#60
0$
0&
#70
1!
b1 7
1$
#80
0$
#90
b1 3
b10 7
1*
1$
#100
0$
#110
0"
0*
b10 3
1+
b0 .
b1 0
b1010101 ,
b1010101 /
b1010101 2
1$
#120
0$
#130
b11 3
1$
#140
0$
#150
b100 3
1$
#160
0$
#170
14
b0 3
1$
#180
0$
#190
b11 7
b1 3
04
1$
#200
0$
#210
b10 3
1$
#220
0$
#230
b11 3
1$
#240
0$
#250
b100 3
1$
#260
0$
#270
14
b0 3
1$
#280
0$
#290
b1 3
04
b1 5
1$
#300
0$
#310
b10 3
1$
#320
0$
#330
b11 3
1$
#340
0$
#350
b100 3
1$
#360
0$
#370
14
b0 3
1$
#380
0$
#390
b10 5
b1 3
04
1$
#400
0$
#410
b10 3
1$
#420
0$
#430
b11 3
1$
#440
0$
#450
b100 3
1$
#460
0$
#470
14
b0 3
1$
#480
0$
#490
b1 3
04
b11 5
1$
#500
0$
#510
b10 3
1$
#520
0$
#530
b11 3
1$
#540
0$
#550
b100 3
1$
#560
0$
#570
14
b0 3
1$
#580
0$
#590
b100 5
b1 3
04
1$
#600
0$
#610
b10 3
1$
#620
0$
#630
b11 3
1$
#640
0$
#650
b100 3
1$
#660
0$
#670
14
b0 3
1$
#680
0$
#690
b1 3
04
b101 5
1$
#700
0$
#710
b10 3
1$
#720
0$
#730
b11 3
1$
#740
0$
#750
b100 3
1$
#760
0$
#770
14
b0 3
1$
#780
0$
#790
b110 5
b1 3
04
1$
#800
0$
#810
b10 3
1$
#820
0$
#830
b11 3
1$
#840
0$
#850
b100 3
1$
#860
0$
#870
14
b0 3
1$
#880
0$
#890
b1 3
04
b111 5
1$
#900
0$
#910
b10 3
1$
#920
0$
#930
b11 3
1$
#940
0$
#950
b100 3
1$
#960
0$
#970
14
b0 3
1$
